{
  "data": [
    {
      "customdata": [
        [
          "https:\u002f\u002fpartigabor.github.io\u002fspice\u002fbook\u002fmaterials\u002fallspice",
          "Pimenta dioica",
          "Myrtaceae",
          "S. Mexico to C. America; Caribbean",
          "\u0641\u0644\u0641\u0644 \u0625\u0641\u0631\u0646\u062c\u064a",
          "fulful ifranj\u012b",
          "\u591a\u9999\u679c",
          "du\u014dxi\u0101nggu\u01d2",
          0.85,
          "-77",
          "18",
          2.85
        ],
        [
          "https:\u002f\u002fpartigabor.github.io\u002fspice\u002fbook\u002fmaterials\u002fclove",
          "Syzygium aromaticum",
          "Myrtaceae",
          "Moluccas (Indonesia)",
          "\u0642\u0631\u0646\u0641\u0644",
          "qaranful",
          "\u4e01\u9999",
          "d\u012bngxi\u0101ng",
          9.0,
          "127",
          "0",
          11.0
        ]
      ],
      "geo": "geo",
      "hovertemplate": "\u003cb\u003e%{text}\u003c\u002fb\u003e\u003cbr\u003e\u003cbr\u003eSpecies: \u003ci\u003e%{customdata[1]}\u003c\u002fi\u003e\u003cbr\u003eFamily: \u003ci\u003e%{customdata[2]}\u003c\u002fi\u003e\u003cbr\u003eRegion of origin: %{customdata[3]}\u003cbr\u003eArabic: %{customdata[4]} \u003ci\u003e%{customdata[5]}\u003c\u002fi\u003e\u003cbr\u003eChinese: %{customdata[6]} \u003ci\u003e%{customdata[7]}\u003c\u002fi\u003e\u003cbr\u003eSpreadability: %{customdata[8]:.2f}\u003cbr\u003e\u003cextra\u003e\u003c\u002fextra\u003e",
      "hovertext": [
        "allspice",
        "clove"
      ],
      "lat": [
        "18",
        "0"
      ],
      "legendgroup": "Myrtaceae",
      "lon": [
        "-77",
        "127"
      ],
      "marker": {
        "color": "#5f4690",
        "opacity": 0.7,
        "size": [
          2.85,
          11.0
        ],
        "sizemode": "area",
        "sizeref": 0.0537109375,
        "symbol": "circle",
        "line": {
          "color": "rgba(0,0,0,0)",
          "width": 1
        }
      },
      "mode": "markers+text",
      "name": "Myrtaceae",
      "showlegend": true,
      "text": [
        "allspice",
        "clove"
      ],
      "type": "scattergeo",
      "textfont": {
        "color": "black",
        "family": "Serif",
        "size": 14
      },
      "textposition": "middle right"
    },
    {
      "customdata": [
        [
          "https:\u002f\u002fpartigabor.github.io\u002fspice\u002fbook\u002fmaterials\u002fanise",
          "Pimpinella anisum",
          "Apiaceae",
          null,
          "\u0623\u0646\u064a\u0633\u0648\u0646",
          "an\u012bs\u016bn",
          "\u8334\u82b9",
          "hu\u00edq\u00edn",
          10.5,
          "35",
          "39",
          12.5
        ],
        [
          "https:\u002f\u002fpartigabor.github.io\u002fspice\u002fbook\u002fmaterials\u002fasafoetida",
          "Ferula foetida",
          "Apiaceae",
          "Iran; W. and C. Asia",
          "\u062d\u0644\u062a\u06cc\u062a",
          "\u1e25ilt\u012bt",
          "\u963f\u9b4f",
          "\u0101w\u00e8i",
          0.12,
          "55",
          "35",
          2.12
        ],
        [
          "https:\u002f\u002fpartigabor.github.io\u002fspice\u002fbook\u002fmaterials\u002fcaraway",
          "Carum carvi",
          "Apiaceae",
          "Mediterranean; Eurasia",
          "\u0643\u0631\u0627\u0648\u064a\u0627",
          "kar\u0101wiy\u0101",
          "\u845b\u7e37\u5b50",
          "g\u011b\u200bl\u01da\u200bzi",
          0.85,
          "69",
          "45",
          2.85
        ],
        [
          "https:\u002f\u002fpartigabor.github.io\u002fspice\u002fbook\u002fmaterials\u002fcoriander",
          "Coriandrum sativum",
          "Apiaceae",
          "Mediterranean; W. Asia; India; SW As",
          "\u0643\u0632\u0628\u0631\u0629",
          "kuzbara",
          "\u82ab\u837d",
          "y\u00e1n\u200bsui",
          15.0,
          "39",
          "35",
          17.0
        ],
        [
          "https:\u002f\u002fpartigabor.github.io\u002fspice\u002fbook\u002fmaterials\u002fcumin",
          "Cuminum cyminum",
          "Apiaceae",
          "W. \\& C. Asia; India ",
          "\u0643\u0645\u0648\u0646 ",
          "kamm\u016bn",
          "\u5b5c\u7136",
          "z\u012b\u200br\u00e1n",
          8.67,
          "53",
          "32",
          10.67
        ],
        [
          "https:\u002f\u002fpartigabor.github.io\u002fspice\u002fbook\u002fmaterials\u002fdill",
          "Anethum graveolens",
          "Apiaceae",
          "Nort Africa; West Asia",
          "\u0634\u0628\u062a",
          "shibitt",
          "\u8494\u863f",
          "sh\u00edlu\u00f3",
          12.18,
          "30",
          "28",
          14.18
        ],
        [
          "https:\u002f\u002fpartigabor.github.io\u002fspice\u002fbook\u002fmaterials\u002ffennel",
          "Foeniculum vulgare",
          "Apiaceae",
          "Med",
          "\u0634\u0645\u0631",
          "shamar",
          "\u8334\u9999",
          "hu\u00edxi\u0101ng",
          2.78,
          "42",
          "29",
          4.779999999999999
        ]
      ],
      "geo": "geo",
      "hovertemplate": "\u003cb\u003e%{text}\u003c\u002fb\u003e\u003cbr\u003e\u003cbr\u003eSpecies: \u003ci\u003e%{customdata[1]}\u003c\u002fi\u003e\u003cbr\u003eFamily: \u003ci\u003e%{customdata[2]}\u003c\u002fi\u003e\u003cbr\u003eRegion of origin: %{customdata[3]}\u003cbr\u003eArabic: %{customdata[4]} \u003ci\u003e%{customdata[5]}\u003c\u002fi\u003e\u003cbr\u003eChinese: %{customdata[6]} \u003ci\u003e%{customdata[7]}\u003c\u002fi\u003e\u003cbr\u003eSpreadability: %{customdata[8]:.2f}\u003cbr\u003e\u003cextra\u003e\u003c\u002fextra\u003e",
      "hovertext": [
        "anise",
        "asafoetida",
        "caraway",
        "coriander",
        "cumin",
        "dill",
        "fennel"
      ],
      "lat": [
        "39",
        "35",
        "45",
        "35",
        "32",
        "28",
        "29"
      ],
      "legendgroup": "Apiaceae",
      "lon": [
        "35",
        "55",
        "69",
        "39",
        "53",
        "30",
        "42"
      ],
      "marker": {
        "color": "#1d6996",
        "opacity": 0.7,
        "size": [
          12.5,
          2.12,
          2.85,
          17.0,
          10.67,
          14.18,
          4.779999999999999
        ],
        "sizemode": "area",
        "sizeref": 0.0537109375,
        "symbol": "circle",
        "line": {
          "color": "rgba(0,0,0,0)",
          "width": 1
        }
      },
      "mode": "markers+text",
      "name": "Apiaceae",
      "showlegend": true,
      "text": [
        "anise",
        "asafoetida",
        "caraway",
        "coriander",
        "cumin",
        "dill",
        "fennel"
      ],
      "type": "scattergeo",
      "textfont": {
        "color": "black",
        "family": "Serif",
        "size": 14
      },
      "textposition": "middle right"
    },
    {
      "customdata": [
        [
          "https:\u002f\u002fpartigabor.github.io\u002fspice\u002fbook\u002fmaterials\u002fcardamom",
          "Elettaria cardamomum",
          "Zingiberaceae",
          "India",
          "\u0647\u0627\u0644",
          "h\u0101l",
          "\u8c46\u853b",
          "d\u00f2uk\u00f2u",
          3.5,
          "75",
          "16",
          5.5
        ],
        [
          "https:\u002f\u002fpartigabor.github.io\u002fspice\u002fbook\u002fmaterials\u002fginger",
          "Zingiber officinale",
          "Zingiberaceae",
          "South East Asia; India (secondary)",
          "\u0632\u0646\u062c\u0628\u064a\u0644",
          "zanjab\u012bl",
          "\u8591",
          "ji\u0101ng",
          8.75,
          "95",
          "24",
          10.75
        ],
        [
          "https:\u002f\u002fpartigabor.github.io\u002fspice\u002fbook\u002fmaterials\u002fturmeric",
          "Curcuma longa",
          "Zingiberaceae",
          "India",
          "\u0643\u0631\u0643\u0645",
          "kurkum",
          "\u8591\u9ec3",
          "ji\u0101nghu\u00e1ng",
          53.0,
          "79",
          "12",
          55.0
        ]
      ],
      "geo": "geo",
      "hovertemplate": "\u003cb\u003e%{text}\u003c\u002fb\u003e\u003cbr\u003e\u003cbr\u003eSpecies: \u003ci\u003e%{customdata[1]}\u003c\u002fi\u003e\u003cbr\u003eFamily: \u003ci\u003e%{customdata[2]}\u003c\u002fi\u003e\u003cbr\u003eRegion of origin: %{customdata[3]}\u003cbr\u003eArabic: %{customdata[4]} \u003ci\u003e%{customdata[5]}\u003c\u002fi\u003e\u003cbr\u003eChinese: %{customdata[6]} \u003ci\u003e%{customdata[7]}\u003c\u002fi\u003e\u003cbr\u003eSpreadability: %{customdata[8]:.2f}\u003cbr\u003e\u003cextra\u003e\u003c\u002fextra\u003e",
      "hovertext": [
        "cardamom",
        "ginger",
        "turmeric"
      ],
      "lat": [
        "16",
        "24",
        "12"
      ],
      "legendgroup": "Zingiberaceae",
      "lon": [
        "75",
        "95",
        "79"
      ],
      "marker": {
        "color": "#38a6a5",
        "opacity": 0.7,
        "size": [
          5.5,
          10.75,
          55.0
        ],
        "sizemode": "area",
        "sizeref": 0.0537109375,
        "symbol": "circle",
        "line": {
          "color": "rgba(0,0,0,0)",
          "width": 1
        }
      },
      "mode": "markers+text",
      "name": "Zingiberaceae",
      "showlegend": true,
      "text": [
        "cardamom",
        "ginger",
        "turmeric"
      ],
      "type": "scattergeo",
      "textfont": {
        "color": "black",
        "family": "Serif",
        "size": 14
      },
      "textposition": "middle right"
    },
    {
      "customdata": [
        [
          "https:\u002f\u002fpartigabor.github.io\u002fspice\u002fbook\u002fmaterials\u002fcassia",
          "Cinnamomum cassia",
          "Lauraceae",
          null,
          "\u0633\u0644\u064a\u062e\u0629",
          "sal\u012bkha",
          "\u8089\u6842",
          "r\u00f2ugu\u00ec",
          15.0,
          "111",
          "22",
          17.0
        ],
        [
          "https:\u002f\u002fpartigabor.github.io\u002fspice\u002fbook\u002fmaterials\u002fcinnamon",
          "Cinnamomum verum",
          "Lauraceae",
          "Sri Lanka; SW. India",
          "\u0642\u0631\u0641\u0629",
          "qirfa",
          "\u932b\u862d\u8089\u6842",
          "x\u012bl\u00e1nr\u00f2ugu\u00ec",
          26.0,
          "81",
          "7",
          28.0
        ]
      ],
      "geo": "geo",
      "hovertemplate": "\u003cb\u003e%{text}\u003c\u002fb\u003e\u003cbr\u003e\u003cbr\u003eSpecies: \u003ci\u003e%{customdata[1]}\u003c\u002fi\u003e\u003cbr\u003eFamily: \u003ci\u003e%{customdata[2]}\u003c\u002fi\u003e\u003cbr\u003eRegion of origin: %{customdata[3]}\u003cbr\u003eArabic: %{customdata[4]} \u003ci\u003e%{customdata[5]}\u003c\u002fi\u003e\u003cbr\u003eChinese: %{customdata[6]} \u003ci\u003e%{customdata[7]}\u003c\u002fi\u003e\u003cbr\u003eSpreadability: %{customdata[8]:.2f}\u003cbr\u003e\u003cextra\u003e\u003c\u002fextra\u003e",
      "hovertext": [
        "cassia",
        "cinnamon"
      ],
      "lat": [
        "22",
        "7"
      ],
      "legendgroup": "Lauraceae",
      "lon": [
        "111",
        "81"
      ],
      "marker": {
        "color": "#0f8554",
        "opacity": 0.7,
        "size": [
          17.0,
          28.0
        ],
        "sizemode": "area",
        "sizeref": 0.0537109375,
        "symbol": "circle",
        "line": {
          "color": "rgba(0,0,0,0)",
          "width": 1
        }
      },
      "mode": "markers+text",
      "name": "Lauraceae",
      "showlegend": true,
      "text": [
        "cassia",
        "cinnamon"
      ],
      "type": "scattergeo",
      "textfont": {
        "color": "black",
        "family": "Serif",
        "size": 14
      },
      "textposition": "middle right"
    },
    {
      "customdata": [
        [
          "https:\u002f\u002fpartigabor.github.io\u002fspice\u002fbook\u002fmaterials\u002fchile",
          "Capsicum annuum",
          "Solanaceae",
          "Central America",
          "\u0641\u0644\u0641\u0644 \u062d\u0627\u0631",
          "fulful h\u0101rr",
          "\u8fa3\u6912",
          "l\u00e0ji\u0101o",
          17.14,
          "-85",
          "12",
          19.14
        ]
      ],
      "geo": "geo",
      "hovertemplate": "\u003cb\u003e%{text}\u003c\u002fb\u003e\u003cbr\u003e\u003cbr\u003eSpecies: \u003ci\u003e%{customdata[1]}\u003c\u002fi\u003e\u003cbr\u003eFamily: \u003ci\u003e%{customdata[2]}\u003c\u002fi\u003e\u003cbr\u003eRegion of origin: %{customdata[3]}\u003cbr\u003eArabic: %{customdata[4]} \u003ci\u003e%{customdata[5]}\u003c\u002fi\u003e\u003cbr\u003eChinese: %{customdata[6]} \u003ci\u003e%{customdata[7]}\u003c\u002fi\u003e\u003cbr\u003eSpreadability: %{customdata[8]:.2f}\u003cbr\u003e\u003cextra\u003e\u003c\u002fextra\u003e",
      "hovertext": [
        "chile"
      ],
      "lat": [
        "12"
      ],
      "legendgroup": "Solanaceae",
      "lon": [
        "-85"
      ],
      "marker": {
        "color": "#73af48",
        "opacity": 0.7,
        "size": [
          19.14
        ],
        "sizemode": "area",
        "sizeref": 0.0537109375,
        "symbol": "circle",
        "line": {
          "color": "rgba(0,0,0,0)",
          "width": 1
        }
      },
      "mode": "markers+text",
      "name": "Solanaceae",
      "showlegend": true,
      "text": [
        "chile"
      ],
      "type": "scattergeo",
      "textfont": {
        "color": "black",
        "family": "Serif",
        "size": 14
      },
      "textposition": "middle right"
    },
    {
      "customdata": [
        [
          "https:\u002f\u002fpartigabor.github.io\u002fspice\u002fbook\u002fmaterials\u002ffenugreek",
          "Trigonella foenum-graecum",
          "Fabaceae",
          "S Eur; W As",
          "\u062d\u0644\u0628\u0629",
          "\u1e25ulba",
          "\u80e1\u8606\u5df4",
          "h\u00fal\u00fab\u0101",
          17.0,
          "67",
          "33",
          19.0
        ]
      ],
      "geo": "geo",
      "hovertemplate": "\u003cb\u003e%{text}\u003c\u002fb\u003e\u003cbr\u003e\u003cbr\u003eSpecies: \u003ci\u003e%{customdata[1]}\u003c\u002fi\u003e\u003cbr\u003eFamily: \u003ci\u003e%{customdata[2]}\u003c\u002fi\u003e\u003cbr\u003eRegion of origin: %{customdata[3]}\u003cbr\u003eArabic: %{customdata[4]} \u003ci\u003e%{customdata[5]}\u003c\u002fi\u003e\u003cbr\u003eChinese: %{customdata[6]} \u003ci\u003e%{customdata[7]}\u003c\u002fi\u003e\u003cbr\u003eSpreadability: %{customdata[8]:.2f}\u003cbr\u003e\u003cextra\u003e\u003c\u002fextra\u003e",
      "hovertext": [
        "fenugreek"
      ],
      "lat": [
        "33"
      ],
      "legendgroup": "Fabaceae",
      "lon": [
        "67"
      ],
      "marker": {
        "color": "#edae08",
        "opacity": 0.7,
        "size": [
          19.0
        ],
        "sizemode": "area",
        "sizeref": 0.0537109375,
        "symbol": "circle",
        "line": {
          "color": "rgba(0,0,0,0)",
          "width": 1
        }
      },
      "mode": "markers+text",
      "name": "Fabaceae",
      "showlegend": true,
      "text": [
        "fenugreek"
      ],
      "type": "scattergeo",
      "textfont": {
        "color": "black",
        "family": "Serif",
        "size": 14
      },
      "textposition": "middle right"
    },
    {
      "customdata": [
        [
          "https:\u002f\u002fpartigabor.github.io\u002fspice\u002fbook\u002fmaterials\u002flong_pepper",
          "Piper longum",
          "Piperaceae",
          "E. Himalaya to S. China; Indo-China",
          "\u062f\u0627\u0631\u0641\u0644\u0641\u0644",
          "d\u0101rfilfil",
          "\u84fd\u64a5",
          "b\u00ecb\u014d",
          0.7,
          "80",
          "23",
          2.7
        ],
        [
          "https:\u002f\u002fpartigabor.github.io\u002fspice\u002fbook\u002fmaterials\u002fpepper",
          "Piper nigrum",
          "Piperaceae",
          "Malabar coast (South India)",
          "\u0641\u0644\u0641\u0644",
          "filfil, fulful",
          "\u80e1\u6912",
          "h\u00faji\u0101o",
          37.0,
          "76",
          "14",
          39.0
        ]
      ],
      "geo": "geo",
      "hovertemplate": "\u003cb\u003e%{text}\u003c\u002fb\u003e\u003cbr\u003e\u003cbr\u003eSpecies: \u003ci\u003e%{customdata[1]}\u003c\u002fi\u003e\u003cbr\u003eFamily: \u003ci\u003e%{customdata[2]}\u003c\u002fi\u003e\u003cbr\u003eRegion of origin: %{customdata[3]}\u003cbr\u003eArabic: %{customdata[4]} \u003ci\u003e%{customdata[5]}\u003c\u002fi\u003e\u003cbr\u003eChinese: %{customdata[6]} \u003ci\u003e%{customdata[7]}\u003c\u002fi\u003e\u003cbr\u003eSpreadability: %{customdata[8]:.2f}\u003cbr\u003e\u003cextra\u003e\u003c\u002fextra\u003e",
      "hovertext": [
        "long pepper",
        "pepper"
      ],
      "lat": [
        "23",
        "14"
      ],
      "legendgroup": "Piperaceae",
      "lon": [
        "80",
        "76"
      ],
      "marker": {
        "color": "#e17909",
        "opacity": 0.7,
        "size": [
          2.7,
          39.0
        ],
        "sizemode": "area",
        "sizeref": 0.0537109375,
        "symbol": "circle",
        "line": {
          "color": "rgba(0,0,0,0)",
          "width": 1
        }
      },
      "mode": "markers+text",
      "name": "Piperaceae",
      "showlegend": true,
      "text": [
        "long pepper",
        "pepper"
      ],
      "type": "scattergeo",
      "textfont": {
        "color": "black",
        "family": "Serif",
        "size": 14
      },
      "textposition": "middle right"
    },
    {
      "customdata": [
        [
          "https:\u002f\u002fpartigabor.github.io\u002fspice\u002fbook\u002fmaterials\u002fmace",
          "Myristica fragrans",
          "Myristicaceae",
          "Moluccas (Indonesia)",
          "\u0628\u0633\u0628\u0627\u0633\u0629",
          "basb\u0101sa",
          "\u8089\u8c46\u853b\u76ae",
          "r\u00f2ud\u00f2uk\u00f2up\u00ed",
          14.0,
          "130",
          "-6",
          16.0
        ],
        [
          "https:\u002f\u002fpartigabor.github.io\u002fspice\u002fbook\u002fmaterials\u002fnutmeg",
          "Myristica fragrans",
          "Myristicaceae",
          "Moluccas (Indonesia)",
          "\u062c\u0648\u0632 \u0627\u0644\u0637\u064a\u0628",
          "jawz al-\u1e6d\u012bb",
          "\u8089\u8c46\u853b",
          "r\u00f2ud\u00f2uk\u00f2u",
          14.0,
          "129",
          "-4",
          16.0
        ]
      ],
      "geo": "geo",
      "hovertemplate": "\u003cb\u003e%{text}\u003c\u002fb\u003e\u003cbr\u003e\u003cbr\u003eSpecies: \u003ci\u003e%{customdata[1]}\u003c\u002fi\u003e\u003cbr\u003eFamily: \u003ci\u003e%{customdata[2]}\u003c\u002fi\u003e\u003cbr\u003eRegion of origin: %{customdata[3]}\u003cbr\u003eArabic: %{customdata[4]} \u003ci\u003e%{customdata[5]}\u003c\u002fi\u003e\u003cbr\u003eChinese: %{customdata[6]} \u003ci\u003e%{customdata[7]}\u003c\u002fi\u003e\u003cbr\u003eSpreadability: %{customdata[8]:.2f}\u003cbr\u003e\u003cextra\u003e\u003c\u002fextra\u003e",
      "hovertext": [
        "mace",
        "nutmeg"
      ],
      "lat": [
        "-6",
        "-4"
      ],
      "legendgroup": "Myristicaceae",
      "lon": [
        "130",
        "129"
      ],
      "marker": {
        "color": "#cc503e",
        "opacity": 0.7,
        "size": [
          16.0,
          16.0
        ],
        "sizemode": "area",
        "sizeref": 0.0537109375,
        "symbol": "circle",
        "line": {
          "color": "rgba(0,0,0,0)",
          "width": 1
        }
      },
      "mode": "markers+text",
      "name": "Myristicaceae",
      "showlegend": true,
      "text": [
        "mace",
        "nutmeg"
      ],
      "type": "scattergeo",
      "textfont": {
        "color": "black",
        "family": "Serif",
        "size": 14
      },
      "textposition": "middle right"
    },
    {
      "customdata": [
        [
          "https:\u002f\u002fpartigabor.github.io\u002fspice\u002fbook\u002fmaterials\u002fsaffron",
          "Crocus sativus",
          "Iridaceae",
          "Greece",
          "\u0632\u0639\u0641\u0631\u0627\u0646",
          "za\u02bffar\u0101n",
          "\u85cf\u7d05\u82b1",
          "z\u00e0ngh\u00f3nghu\u0101",
          8.0,
          "22",
          "39",
          10.0
        ]
      ],
      "geo": "geo",
      "hovertemplate": "\u003cb\u003e%{text}\u003c\u002fb\u003e\u003cbr\u003e\u003cbr\u003eSpecies: \u003ci\u003e%{customdata[1]}\u003c\u002fi\u003e\u003cbr\u003eFamily: \u003ci\u003e%{customdata[2]}\u003c\u002fi\u003e\u003cbr\u003eRegion of origin: %{customdata[3]}\u003cbr\u003eArabic: %{customdata[4]} \u003ci\u003e%{customdata[5]}\u003c\u002fi\u003e\u003cbr\u003eChinese: %{customdata[6]} \u003ci\u003e%{customdata[7]}\u003c\u002fi\u003e\u003cbr\u003eSpreadability: %{customdata[8]:.2f}\u003cbr\u003e\u003cextra\u003e\u003c\u002fextra\u003e",
      "hovertext": [
        "saffron"
      ],
      "lat": [
        "39"
      ],
      "legendgroup": "Iridaceae",
      "lon": [
        "22"
      ],
      "marker": {
        "color": "#94346e",
        "opacity": 0.7,
        "size": [
          10.0
        ],
        "sizemode": "area",
        "sizeref": 0.0537109375,
        "symbol": "circle",
        "line": {
          "color": "rgba(0,0,0,0)",
          "width": 1
        }
      },
      "mode": "markers+text",
      "name": "Iridaceae",
      "showlegend": true,
      "text": [
        "saffron"
      ],
      "type": "scattergeo",
      "textfont": {
        "color": "black",
        "family": "Serif",
        "size": 14
      },
      "textposition": "middle right"
    },
    {
      "customdata": [
        [
          "https:\u002f\u002fpartigabor.github.io\u002fspice\u002fbook\u002fmaterials\u002fSichuan_pepper",
          "Zanthoxylum bungeanum",
          "Rutaceae",
          "China",
          "\u0641\u0644\u0641\u0644 \u0633\u064a\u062a\u0634\u0648\u0627\u0646",
          "fulful s\u012btshuw\u0101n",
          "\u82b1\u6912",
          "hu\u0101\u200bji\u0101o",
          0.1,
          "105",
          "35",
          2.1
        ]
      ],
      "geo": "geo",
      "hovertemplate": "\u003cb\u003e%{text}\u003c\u002fb\u003e\u003cbr\u003e\u003cbr\u003eSpecies: \u003ci\u003e%{customdata[1]}\u003c\u002fi\u003e\u003cbr\u003eFamily: \u003ci\u003e%{customdata[2]}\u003c\u002fi\u003e\u003cbr\u003eRegion of origin: %{customdata[3]}\u003cbr\u003eArabic: %{customdata[4]} \u003ci\u003e%{customdata[5]}\u003c\u002fi\u003e\u003cbr\u003eChinese: %{customdata[6]} \u003ci\u003e%{customdata[7]}\u003c\u002fi\u003e\u003cbr\u003eSpreadability: %{customdata[8]:.2f}\u003cbr\u003e\u003cextra\u003e\u003c\u002fextra\u003e",
      "hovertext": [
        "Sichuan pepper"
      ],
      "lat": [
        "35"
      ],
      "legendgroup": "Rutaceae",
      "lon": [
        "105"
      ],
      "marker": {
        "color": "#6f4070",
        "opacity": 0.7,
        "size": [
          2.1
        ],
        "sizemode": "area",
        "sizeref": 0.0537109375,
        "symbol": "circle",
        "line": {
          "color": "rgba(0,0,0,0)",
          "width": 1
        }
      },
      "mode": "markers+text",
      "name": "Rutaceae",
      "showlegend": true,
      "text": [
        "Sichuan pepper"
      ],
      "type": "scattergeo",
      "textfont": {
        "color": "black",
        "family": "Serif",
        "size": 14
      },
      "textposition": "middle right"
    },
    {
      "customdata": [
        [
          "https:\u002f\u002fpartigabor.github.io\u002fspice\u002fbook\u002fmaterials\u002fstar_anise",
          "Illicium verum",
          "Schisandraceae",
          "SE. China; Vietnam",
          "\u064a\u0627\u0646\u0633\u0648\u0646 \u0646\u062c\u0645\u064a",
          "y\u0101ns\u016bn najm\u012b",
          "\u516b\u89d2",
          "b\u0101ji\u01ceo",
          1.0,
          "106",
          "18",
          3.0
        ]
      ],
      "geo": "geo",
      "hovertemplate": "\u003cb\u003e%{text}\u003c\u002fb\u003e\u003cbr\u003e\u003cbr\u003eSpecies: \u003ci\u003e%{customdata[1]}\u003c\u002fi\u003e\u003cbr\u003eFamily: \u003ci\u003e%{customdata[2]}\u003c\u002fi\u003e\u003cbr\u003eRegion of origin: %{customdata[3]}\u003cbr\u003eArabic: %{customdata[4]} \u003ci\u003e%{customdata[5]}\u003c\u002fi\u003e\u003cbr\u003eChinese: %{customdata[6]} \u003ci\u003e%{customdata[7]}\u003c\u002fi\u003e\u003cbr\u003eSpreadability: %{customdata[8]:.2f}\u003cbr\u003e\u003cextra\u003e\u003c\u002fextra\u003e",
      "hovertext": [
        "star anise"
      ],
      "lat": [
        "18"
      ],
      "legendgroup": "Schisandraceae",
      "lon": [
        "106"
      ],
      "marker": {
        "color": "#a28aba",
        "opacity": 0.7,
        "size": [
          3.0
        ],
        "sizemode": "area",
        "sizeref": 0.0537109375,
        "symbol": "circle",
        "line": {
          "color": "rgba(0,0,0,0)",
          "width": 1
        }
      },
      "mode": "markers+text",
      "name": "Schisandraceae",
      "showlegend": true,
      "text": [
        "star anise"
      ],
      "type": "scattergeo",
      "textfont": {
        "color": "black",
        "family": "Serif",
        "size": 14
      },
      "textposition": "middle right"
    },
    {
      "customdata": [
        [
          "https:\u002f\u002fpartigabor.github.io\u002fspice\u002fbook\u002fmaterials\u002fvanilla",
          "Vanilla planifolia",
          "Orchidaceae",
          "Tropical America",
          "\u0641\u0627\u0646\u064a\u0644\u064a\u0627",
          "f\u0101n\u012bliy\u0101",
          "\u9999\u8349",
          "xi\u0101ngc\u01ceo",
          2.64,
          "-55",
          "-10",
          4.640000000000001
        ]
      ],
      "geo": "geo",
      "hovertemplate": "\u003cb\u003e%{text}\u003c\u002fb\u003e\u003cbr\u003e\u003cbr\u003eSpecies: \u003ci\u003e%{customdata[1]}\u003c\u002fi\u003e\u003cbr\u003eFamily: \u003ci\u003e%{customdata[2]}\u003c\u002fi\u003e\u003cbr\u003eRegion of origin: %{customdata[3]}\u003cbr\u003eArabic: %{customdata[4]} \u003ci\u003e%{customdata[5]}\u003c\u002fi\u003e\u003cbr\u003eChinese: %{customdata[6]} \u003ci\u003e%{customdata[7]}\u003c\u002fi\u003e\u003cbr\u003eSpreadability: %{customdata[8]:.2f}\u003cbr\u003e\u003cextra\u003e\u003c\u002fextra\u003e",
      "hovertext": [
        "vanilla"
      ],
      "lat": [
        "-10"
      ],
      "legendgroup": "Orchidaceae",
      "lon": [
        "-55"
      ],
      "marker": {
        "color": "#6baed6",
        "opacity": 0.7,
        "size": [
          4.640000000000001
        ],
        "sizemode": "area",
        "sizeref": 0.0537109375,
        "symbol": "circle",
        "line": {
          "color": "rgba(0,0,0,0)",
          "width": 1
        }
      },
      "mode": "markers+text",
      "name": "Orchidaceae",
      "showlegend": true,
      "text": [
        "vanilla"
      ],
      "type": "scattergeo",
      "textfont": {
        "color": "black",
        "family": "Serif",
        "size": 14
      },
      "textposition": "middle right"
    }
  ],
  "layout": {
    "template": {
      "data": {
        "histogram2dcontour": [
          {
            "type": "histogram2dcontour",
            "colorbar": {
              "outlinewidth": 0,
              "ticks": ""
            },
            "colorscale": [
              [
                0.0,
                "#0d0887"
              ],
              [
                0.1111111111111111,
                "#46039f"
              ],
              [
                0.2222222222222222,
                "#7201a8"
              ],
              [
                0.3333333333333333,
                "#9c179e"
              ],
              [
                0.4444444444444444,
                "#bd3786"
              ],
              [
                0.5555555555555556,
                "#d8576b"
              ],
              [
                0.6666666666666666,
                "#ed7953"
              ],
              [
                0.7777777777777778,
                "#fb9f3a"
              ],
              [
                0.8888888888888888,
                "#fdca26"
              ],
              [
                1.0,
                "#f0f921"
              ]
            ]
          }
        ],
        "choropleth": [
          {
            "type": "choropleth",
            "colorbar": {
              "outlinewidth": 0,
              "ticks": ""
            }
          }
        ],
        "histogram2d": [
          {
            "type": "histogram2d",
            "colorbar": {
              "outlinewidth": 0,
              "ticks": ""
            },
            "colorscale": [
              [
                0.0,
                "#0d0887"
              ],
              [
                0.1111111111111111,
                "#46039f"
              ],
              [
                0.2222222222222222,
                "#7201a8"
              ],
              [
                0.3333333333333333,
                "#9c179e"
              ],
              [
                0.4444444444444444,
                "#bd3786"
              ],
              [
                0.5555555555555556,
                "#d8576b"
              ],
              [
                0.6666666666666666,
                "#ed7953"
              ],
              [
                0.7777777777777778,
                "#fb9f3a"
              ],
              [
                0.8888888888888888,
                "#fdca26"
              ],
              [
                1.0,
                "#f0f921"
              ]
            ]
          }
        ],
        "heatmap": [
          {
            "type": "heatmap",
            "colorbar": {
              "outlinewidth": 0,
              "ticks": ""
            },
            "colorscale": [
              [
                0.0,
                "#0d0887"
              ],
              [
                0.1111111111111111,
                "#46039f"
              ],
              [
                0.2222222222222222,
                "#7201a8"
              ],
              [
                0.3333333333333333,
                "#9c179e"
              ],
              [
                0.4444444444444444,
                "#bd3786"
              ],
              [
                0.5555555555555556,
                "#d8576b"
              ],
              [
                0.6666666666666666,
                "#ed7953"
              ],
              [
                0.7777777777777778,
                "#fb9f3a"
              ],
              [
                0.8888888888888888,
                "#fdca26"
              ],
              [
                1.0,
                "#f0f921"
              ]
            ]
          }
        ],
        "heatmapgl": [
          {
            "type": "heatmapgl",
            "colorbar": {
              "outlinewidth": 0,
              "ticks": ""
            },
            "colorscale": [
              [
                0.0,
                "#0d0887"
              ],
              [
                0.1111111111111111,
                "#46039f"
              ],
              [
                0.2222222222222222,
                "#7201a8"
              ],
              [
                0.3333333333333333,
                "#9c179e"
              ],
              [
                0.4444444444444444,
                "#bd3786"
              ],
              [
                0.5555555555555556,
                "#d8576b"
              ],
              [
                0.6666666666666666,
                "#ed7953"
              ],
              [
                0.7777777777777778,
                "#fb9f3a"
              ],
              [
                0.8888888888888888,
                "#fdca26"
              ],
              [
                1.0,
                "#f0f921"
              ]
            ]
          }
        ],
        "contourcarpet": [
          {
            "type": "contourcarpet",
            "colorbar": {
              "outlinewidth": 0,
              "ticks": ""
            }
          }
        ],
        "contour": [
          {
            "type": "contour",
            "colorbar": {
              "outlinewidth": 0,
              "ticks": ""
            },
            "colorscale": [
              [
                0.0,
                "#0d0887"
              ],
              [
                0.1111111111111111,
                "#46039f"
              ],
              [
                0.2222222222222222,
                "#7201a8"
              ],
              [
                0.3333333333333333,
                "#9c179e"
              ],
              [
                0.4444444444444444,
                "#bd3786"
              ],
              [
                0.5555555555555556,
                "#d8576b"
              ],
              [
                0.6666666666666666,
                "#ed7953"
              ],
              [
                0.7777777777777778,
                "#fb9f3a"
              ],
              [
                0.8888888888888888,
                "#fdca26"
              ],
              [
                1.0,
                "#f0f921"
              ]
            ]
          }
        ],
        "surface": [
          {
            "type": "surface",
            "colorbar": {
              "outlinewidth": 0,
              "ticks": ""
            },
            "colorscale": [
              [
                0.0,
                "#0d0887"
              ],
              [
                0.1111111111111111,
                "#46039f"
              ],
              [
                0.2222222222222222,
                "#7201a8"
              ],
              [
                0.3333333333333333,
                "#9c179e"
              ],
              [
                0.4444444444444444,
                "#bd3786"
              ],
              [
                0.5555555555555556,
                "#d8576b"
              ],
              [
                0.6666666666666666,
                "#ed7953"
              ],
              [
                0.7777777777777778,
                "#fb9f3a"
              ],
              [
                0.8888888888888888,
                "#fdca26"
              ],
              [
                1.0,
                "#f0f921"
              ]
            ]
          }
        ],
        "mesh3d": [
          {
            "type": "mesh3d",
            "colorbar": {
              "outlinewidth": 0,
              "ticks": ""
            }
          }
        ],
        "scatter": [
          {
            "fillpattern": {
              "fillmode": "overlay",
              "size": 10,
              "solidity": 0.2
            },
            "type": "scatter"
          }
        ],
        "parcoords": [
          {
            "type": "parcoords",
            "line": {
              "colorbar": {
                "outlinewidth": 0,
                "ticks": ""
              }
            }
          }
        ],
        "scatterpolargl": [
          {
            "type": "scatterpolargl",
            "marker": {
              "colorbar": {
                "outlinewidth": 0,
                "ticks": ""
              }
            }
          }
        ],
        "bar": [
          {
            "error_x": {
              "color": "#2a3f5f"
            },
            "error_y": {
              "color": "#2a3f5f"
            },
            "marker": {
              "line": {
                "color": "#E5ECF6",
                "width": 0.5
              },
              "pattern": {
                "fillmode": "overlay",
                "size": 10,
                "solidity": 0.2
              }
            },
            "type": "bar"
          }
        ],
        "scattergeo": [
          {
            "type": "scattergeo",
            "marker": {
              "colorbar": {
                "outlinewidth": 0,
                "ticks": ""
              }
            }
          }
        ],
        "scatterpolar": [
          {
            "type": "scatterpolar",
            "marker": {
              "colorbar": {
                "outlinewidth": 0,
                "ticks": ""
              }
            }
          }
        ],
        "histogram": [
          {
            "marker": {
              "pattern": {
                "fillmode": "overlay",
                "size": 10,
                "solidity": 0.2
              }
            },
            "type": "histogram"
          }
        ],
        "scattergl": [
          {
            "type": "scattergl",
            "marker": {
              "colorbar": {
                "outlinewidth": 0,
                "ticks": ""
              }
            }
          }
        ],
        "scatter3d": [
          {
            "type": "scatter3d",
            "line": {
              "colorbar": {
                "outlinewidth": 0,
                "ticks": ""
              }
            },
            "marker": {
              "colorbar": {
                "outlinewidth": 0,
                "ticks": ""
              }
            }
          }
        ],
        "scattermapbox": [
          {
            "type": "scattermapbox",
            "marker": {
              "colorbar": {
                "outlinewidth": 0,
                "ticks": ""
              }
            }
          }
        ],
        "scatterternary": [
          {
            "type": "scatterternary",
            "marker": {
              "colorbar": {
                "outlinewidth": 0,
                "ticks": ""
              }
            }
          }
        ],
        "scattercarpet": [
          {
            "type": "scattercarpet",
            "marker": {
              "colorbar": {
                "outlinewidth": 0,
                "ticks": ""
              }
            }
          }
        ],
        "carpet": [
          {
            "aaxis": {
              "endlinecolor": "#2a3f5f",
              "gridcolor": "white",
              "linecolor": "white",
              "minorgridcolor": "white",
              "startlinecolor": "#2a3f5f"
            },
            "baxis": {
              "endlinecolor": "#2a3f5f",
              "gridcolor": "white",
              "linecolor": "white",
              "minorgridcolor": "white",
              "startlinecolor": "#2a3f5f"
            },
            "type": "carpet"
          }
        ],
        "table": [
          {
            "cells": {
              "fill": {
                "color": "#EBF0F8"
              },
              "line": {
                "color": "white"
              }
            },
            "header": {
              "fill": {
                "color": "#C8D4E3"
              },
              "line": {
                "color": "white"
              }
            },
            "type": "table"
          }
        ],
        "barpolar": [
          {
            "marker": {
              "line": {
                "color": "#E5ECF6",
                "width": 0.5
              },
              "pattern": {
                "fillmode": "overlay",
                "size": 10,
                "solidity": 0.2
              }
            },
            "type": "barpolar"
          }
        ],
        "pie": [
          {
            "automargin": true,
            "type": "pie"
          }
        ]
      },
      "layout": {
        "autotypenumbers": "strict",
        "colorway": [
          "#636efa",
          "#EF553B",
          "#00cc96",
          "#ab63fa",
          "#FFA15A",
          "#19d3f3",
          "#FF6692",
          "#B6E880",
          "#FF97FF",
          "#FECB52"
        ],
        "font": {
          "color": "#2a3f5f"
        },
        "hovermode": "closest",
        "hoverlabel": {
          "align": "left"
        },
        "paper_bgcolor": "white",
        "plot_bgcolor": "#E5ECF6",
        "polar": {
          "bgcolor": "#E5ECF6",
          "angularaxis": {
            "gridcolor": "white",
            "linecolor": "white",
            "ticks": ""
          },
          "radialaxis": {
            "gridcolor": "white",
            "linecolor": "white",
            "ticks": ""
          }
        },
        "ternary": {
          "bgcolor": "#E5ECF6",
          "aaxis": {
            "gridcolor": "white",
            "linecolor": "white",
            "ticks": ""
          },
          "baxis": {
            "gridcolor": "white",
            "linecolor": "white",
            "ticks": ""
          },
          "caxis": {
            "gridcolor": "white",
            "linecolor": "white",
            "ticks": ""
          }
        },
        "coloraxis": {
          "colorbar": {
            "outlinewidth": 0,
            "ticks": ""
          }
        },
        "colorscale": {
          "sequential": [
            [
              0.0,
              "#0d0887"
            ],
            [
              0.1111111111111111,
              "#46039f"
            ],
            [
              0.2222222222222222,
              "#7201a8"
            ],
            [
              0.3333333333333333,
              "#9c179e"
            ],
            [
              0.4444444444444444,
              "#bd3786"
            ],
            [
              0.5555555555555556,
              "#d8576b"
            ],
            [
              0.6666666666666666,
              "#ed7953"
            ],
            [
              0.7777777777777778,
              "#fb9f3a"
            ],
            [
              0.8888888888888888,
              "#fdca26"
            ],
            [
              1.0,
              "#f0f921"
            ]
          ],
          "sequentialminus": [
            [
              0.0,
              "#0d0887"
            ],
            [
              0.1111111111111111,
              "#46039f"
            ],
            [
              0.2222222222222222,
              "#7201a8"
            ],
            [
              0.3333333333333333,
              "#9c179e"
            ],
            [
              0.4444444444444444,
              "#bd3786"
            ],
            [
              0.5555555555555556,
              "#d8576b"
            ],
            [
              0.6666666666666666,
              "#ed7953"
            ],
            [
              0.7777777777777778,
              "#fb9f3a"
            ],
            [
              0.8888888888888888,
              "#fdca26"
            ],
            [
              1.0,
              "#f0f921"
            ]
          ],
          "diverging": [
            [
              0,
              "#8e0152"
            ],
            [
              0.1,
              "#c51b7d"
            ],
            [
              0.2,
              "#de77ae"
            ],
            [
              0.3,
              "#f1b6da"
            ],
            [
              0.4,
              "#fde0ef"
            ],
            [
              0.5,
              "#f7f7f7"
            ],
            [
              0.6,
              "#e6f5d0"
            ],
            [
              0.7,
              "#b8e186"
            ],
            [
              0.8,
              "#7fbc41"
            ],
            [
              0.9,
              "#4d9221"
            ],
            [
              1,
              "#276419"
            ]
          ]
        },
        "xaxis": {
          "gridcolor": "white",
          "linecolor": "white",
          "ticks": "",
          "title": {
            "standoff": 15
          },
          "zerolinecolor": "white",
          "automargin": true,
          "zerolinewidth": 2
        },
        "yaxis": {
          "gridcolor": "white",
          "linecolor": "white",
          "ticks": "",
          "title": {
            "standoff": 15
          },
          "zerolinecolor": "white",
          "automargin": true,
          "zerolinewidth": 2
        },
        "scene": {
          "xaxis": {
            "backgroundcolor": "#E5ECF6",
            "gridcolor": "white",
            "linecolor": "white",
            "showbackground": true,
            "ticks": "",
            "zerolinecolor": "white",
            "gridwidth": 2
          },
          "yaxis": {
            "backgroundcolor": "#E5ECF6",
            "gridcolor": "white",
            "linecolor": "white",
            "showbackground": true,
            "ticks": "",
            "zerolinecolor": "white",
            "gridwidth": 2
          },
          "zaxis": {
            "backgroundcolor": "#E5ECF6",
            "gridcolor": "white",
            "linecolor": "white",
            "showbackground": true,
            "ticks": "",
            "zerolinecolor": "white",
            "gridwidth": 2
          }
        },
        "shapedefaults": {
          "line": {
            "color": "#2a3f5f"
          }
        },
        "annotationdefaults": {
          "arrowcolor": "#2a3f5f",
          "arrowhead": 0,
          "arrowwidth": 1
        },
        "geo": {
          "bgcolor": "white",
          "landcolor": "#E5ECF6",
          "subunitcolor": "white",
          "showland": true,
          "showlakes": true,
          "lakecolor": "white"
        },
        "title": {
          "x": 0.05
        },
        "mapbox": {
          "style": "light"
        }
      }
    },
    "geo": {
      "domain": {
        "x": [
          0.0,
          1.0
        ],
        "y": [
          0.0,
          1.0
        ]
      },
      "center": {},
      "projection": {
        "type": "natural earth",
        "scale": 1
      },
      "bgcolor": "rgba(0,0,0,0)",
      "coastlinecolor": "gainsboro",
      "coastlinewidth": 1,
      "countrycolor": "gainsboro",
      "countrywidth": 1,
      "framecolor": "gainsboro",
      "framewidth": 1,
      "lakecolor": "white",
      "landcolor": "gainsboro",
      "oceancolor": "white",
      "resolution": 110,
      "rivercolor": "white",
      "riverwidth": 1,
      "scope": "world",
      "showcoastlines": true,
      "showcountries": false,
      "showframe": true,
      "showlakes": true,
      "showland": true,
      "showocean": true,
      "showrivers": true,
      "showsubunits": false,
      "subunitcolor": "gainsboro",
      "subunitwidth": 1
    },
    "legend": {
      "title": {
        "text": "family",
        "font": {
          "color": "black",
          "family": "Serif",
          "size": 18
        }
      },
      "tracegroupgap": 0,
      "itemsizing": "constant",
      "font": {
        "color": "black",
        "family": "Serif",
        "size": 14
      },
      "bgcolor": "rgba(255,255,255,0.5)",
      "orientation": "v",
      "traceorder": "normal",
      "x": 0,
      "xanchor": "left",
      "y": 0,
      "yanchor": "bottom"
    },
    "margin": {
      "t": 0,
      "b": 0,
      "l": 0,
      "r": 0
    },
    "hoverlabel": {
      "font": {
        "size": 14,
        "family": "Serif"
      }
    },
    "title": {
      "font": {
        "color": "black",
        "family": "Serif",
        "size": 20
      },
      "text": "",
      "x": 0.5,
      "xanchor": "center",
      "y": 0.98,
      "yanchor": "top"
    },
    "paper_bgcolor": "rgba(0,0,0,0)",
    "plot_bgcolor": "rgba(0,0,0,0)",
    "showlegend": true,
    "annotations": [
      {
        "font": {
          "color": "black",
          "family": "Serif",
          "size": 14
        },
        "name": "info",
        "opacity": 0.9,
        "showarrow": false,
        "text": ".",
        "x": 0.5,
        "xref": "paper",
        "y": 0.05,
        "yref": "paper"
      },
      {
        "font": {
          "color": "lightgray",
          "family": "Serif",
          "size": 8
        },
        "name": "copyright",
        "opacity": 0.9,
        "showarrow": false,
        "text": "\u00a9 G\u00e1bor Parti, 2023",
        "x": 0.5,
        "xref": "paper",
        "y": 0,
        "yref": "paper"
      }
    ],
    "images": [
      {
        "sizex": 0.15,
        "sizey": 0.15,
        "source": "https:\u002f\u002fupload.wikimedia.org\u002fwikipedia\u002fen\u002fthumb\u002f9\u002f9e\u002fPolyU_Logo_with_wordmark.svg\u002f1024px-PolyU_Logo_with_wordmark.svg.png",
        "x": 1,
        "xanchor": "right",
        "y": 0,
        "yanchor": "bottom"
      }
    ]
  }
}